social_content/__init__.py
social_content/twitter.py
social_content/weibo.py
social_content/__pycache__/__init__.cpython-39.pyc
social_content/__pycache__/twitter.cpython-39.pyc
social_content/__pycache__/weibo.cpython-39.pyc
social_content-0.0.1a0.dist-info/LICENSE
social_content-0.0.1a0.dist-info/METADATA
social_content-0.0.1a0.dist-info/WHEEL
social_content-0.0.1a0.dist-info/top_level.txt
social_content-0.0.1a0.dist-info/RECORD
